<annotation>
 <folder>test_set</folder>
 <filename>0a7951a0-1ea6-4696-ab66-4283da30f4e2.jpeg</filename>
 <path>/Users/yi.su/workspace/DS/intelligent_parking/image_data/test_set/0a7951a0-1ea6-4696-ab66-4283da30f4e2.jpeg</path>
 <source>
  <database>Unknown</database>
 </source>
 <size>
  <width>454</width>
  <height>605</height>
  <depth>3</depth>
</size>
<segmented>0</segmented>
 <object>
  <name>scooter</name>
  <pose>Unspecified</pose>
  <truncated>0</truncated>
  <difficult>0</difficult>
  <bndbox>
   <xmin>144</xmin>
   <ymin>120</ymin>
   <xmax>428</xmax>
   <ymax>525</ymax>
  </bndbox>
 </object>
</annotation>