<annotation>
 <folder>test_set</folder>
 <filename>0f62f257-7622-4d63-b8ba-48ec77990196.jpeg</filename>
 <path>/Users/yi.su/workspace/DS/intelligent_parking/image_data/test_set/0f62f257-7622-4d63-b8ba-48ec77990196.jpeg</path>
 <source>
  <database>Unknown</database>
 </source>
 <size>
  <width>454</width>
  <height>605</height>
  <depth>3</depth>
</size>
<segmented>0</segmented>
 <object>
  <name>scooter</name>
  <pose>Unspecified</pose>
  <truncated>0</truncated>
  <difficult>0</difficult>
  <bndbox>
   <xmin>127</xmin>
   <ymin>257</ymin>
   <xmax>306</xmax>
   <ymax>498</ymax>
  </bndbox>
 </object>
</annotation>