<annotation>
	<folder>close_to_road</folder>
	<filename>23JG5UFFSAJRB.jpeg</filename>
	<path>/Users/yi.su/workspace/DS/juicer_deploy_parking/data/too_close_to_road_data/close_to_road/23JG5UFFSAJRB.jpeg</path>
	<source>
		<database>Unknown</database>
	</source>
	<size>
		<width>3024</width>
		<height>4032</height>
		<depth>3</depth>
	</size>
	<segmented>0</segmented>
	<object>
		<name>too close</name>
		<pose>Unspecified</pose>
		<truncated>0</truncated>
		<difficult>0</difficult>
		<bndbox>
			<xmin>573</xmin>
			<ymin>2851</ymin>
			<xmax>1035</xmax>
			<ymax>3251</ymax>
		</bndbox>
	</object>
	<object>
		<name>too close</name>
		<pose>Unspecified</pose>
		<truncated>0</truncated>
		<difficult>0</difficult>
		<bndbox>
			<xmin>902</xmin>
			<ymin>2632</ymin>
			<xmax>1273</xmax>
			<ymax>2970</ymax>
		</bndbox>
	</object>
	<object>
		<name>too close</name>
		<pose>Unspecified</pose>
		<truncated>0</truncated>
		<difficult>0</difficult>
		<bndbox>
			<xmin>1069</xmin>
			<ymin>2427</ymin>
			<xmax>1507</xmax>
			<ymax>2765</ymax>
		</bndbox>
	</object>
	<object>
		<name>too close</name>
		<pose>Unspecified</pose>
		<truncated>0</truncated>
		<difficult>0</difficult>
		<bndbox>
			<xmin>1254</xmin>
			<ymin>2251</ymin>
			<xmax>1664</xmax>
			<ymax>2560</ymax>
		</bndbox>
	</object>
</annotation>
