<annotation>
 <folder>test_set</folder>
 <filename>2ccf6afb-6d18-4b01-b187-b8643095ea99.jpeg</filename>
 <path>/Users/yi.su/workspace/DS/intelligent_parking/image_data/test_set/2ccf6afb-6d18-4b01-b187-b8643095ea99.jpeg</path>
 <source>
  <database>Unknown</database>
 </source>
 <size>
  <width>454</width>
  <height>605</height>
  <depth>3</depth>
</size>
<segmented>0</segmented>
 <object>
  <name>scooter</name>
  <pose>Unspecified</pose>
  <truncated>0</truncated>
  <difficult>0</difficult>
  <bndbox>
   <xmin>117</xmin>
   <ymin>129</ymin>
   <xmax>325</xmax>
   <ymax>429</ymax>
  </bndbox>
 </object>
</annotation>