<annotation>
 <folder>test_set</folder>
 <filename>888e2c61-0be7-495f-8b32-f7afb5f1df4e.jpeg</filename>
 <path>/Users/yi.su/workspace/DS/intelligent_parking/image_data/test_set/888e2c61-0be7-495f-8b32-f7afb5f1df4e.jpeg</path>
 <source>
  <database>Unknown</database>
 </source>
 <size>
  <width>454</width>
  <height>605</height>
  <depth>3</depth>
</size>
<segmented>0</segmented>
 <object>
  <name>scooter</name>
  <pose>Unspecified</pose>
  <truncated>0</truncated>
  <difficult>0</difficult>
  <bndbox>
   <xmin>187</xmin>
   <ymin>191</ymin>
   <xmax>350</xmax>
   <ymax>418</ymax>
  </bndbox>
 </object>
</annotation>