<annotation>
 <folder>test_set</folder>
 <filename>927318a9-22a6-43c5-9efb-00fbeb34f5e7.jpeg</filename>
 <path>/Users/yi.su/workspace/DS/intelligent_parking/image_data/test_set/927318a9-22a6-43c5-9efb-00fbeb34f5e7.jpeg</path>
 <source>
  <database>Unknown</database>
 </source>
 <size>
  <width>454</width>
  <height>605</height>
  <depth>3</depth>
</size>
<segmented>0</segmented>
 <object>
  <name>scooter</name>
  <pose>Unspecified</pose>
  <truncated>0</truncated>
  <difficult>0</difficult>
  <bndbox>
   <xmin>88</xmin>
   <ymin>97</ymin>
   <xmax>375</xmax>
   <ymax>483</ymax>
  </bndbox>
 </object>
</annotation>