<annotation>
 <folder>test_set</folder>
 <filename>bf96f7f1-535a-43bc-abe2-c78b860121ba.jpeg</filename>
 <path>/Users/yi.su/workspace/DS/intelligent_parking/image_data/test_set/bf96f7f1-535a-43bc-abe2-c78b860121ba.jpeg</path>
 <source>
  <database>Unknown</database>
 </source>
 <size>
  <width>368</width>
  <height>490</height>
  <depth>3</depth>
</size>
<segmented>0</segmented>
 <object>
  <name>scooter</name>
  <pose>Unspecified</pose>
  <truncated>0</truncated>
  <difficult>0</difficult>
  <bndbox>
   <xmin>153</xmin>
   <ymin>150</ymin>
   <xmax>302</xmax>
   <ymax>384</ymax>
  </bndbox>
 </object>
</annotation>