<annotation>
 <folder>test_set</folder>
 <filename>c2463147-67fa-4bd8-bf77-dc0e29daab7f.jpeg</filename>
 <path>/Users/yi.su/workspace/DS/intelligent_parking/image_data/test_set/c2463147-67fa-4bd8-bf77-dc0e29daab7f.jpeg</path>
 <source>
  <database>Unknown</database>
 </source>
 <size>
  <width>454</width>
  <height>605</height>
  <depth>3</depth>
</size>
<segmented>0</segmented>
 <object>
  <name>scooter</name>
  <pose>Unspecified</pose>
  <truncated>0</truncated>
  <difficult>0</difficult>
  <bndbox>
   <xmin>150</xmin>
   <ymin>131</ymin>
   <xmax>269</xmax>
   <ymax>418</ymax>
  </bndbox>
 </object>
</annotation>