<annotation>
 <folder>test_set</folder>
 <filename>f740f307-1052-4cf7-936f-61237806d147.jpeg</filename>
 <path>/Users/yi.su/workspace/DS/intelligent_parking/image_data/test_set/f740f307-1052-4cf7-936f-61237806d147.jpeg</path>
 <source>
  <database>Unknown</database>
 </source>
 <size>
  <width>454</width>
  <height>605</height>
  <depth>3</depth>
</size>
<segmented>0</segmented>
 <object>
  <name>scooter</name>
  <pose>Unspecified</pose>
  <truncated>0</truncated>
  <difficult>0</difficult>
  <bndbox>
   <xmin>17</xmin>
   <ymin>246</ymin>
   <xmax>430</xmax>
   <ymax>605</ymax>
  </bndbox>
 </object>
</annotation>