<annotation>
 <folder>test_set</folder>
 <filename>f833d58a-eb48-4c62-b340-b6863c21b889.jpeg</filename>
 <path>/Users/yi.su/workspace/DS/intelligent_parking/image_data/test_set/f833d58a-eb48-4c62-b340-b6863c21b889.jpeg</path>
 <source>
  <database>Unknown</database>
 </source>
 <size>
  <width>454</width>
  <height>605</height>
  <depth>3</depth>
</size>
<segmented>0</segmented>
 <object>
  <name>scooter</name>
  <pose>Unspecified</pose>
  <truncated>0</truncated>
  <difficult>0</difficult>
  <bndbox>
   <xmin>148</xmin>
   <ymin>208</ymin>
   <xmax>338</xmax>
   <ymax>477</ymax>
  </bndbox>
 </object>
</annotation>