<annotation>
	<folder>scooter_bounding_box</folder>
	<filename>0e6c6df2-2c31-448e-8f44-e8c998ecd64c.jpeg</filename>
	<path>/Users/yi.su/workspace/DS/intelligent_parking/image_data/scooter_bounding_box/0e6c6df2-2c31-448e-8f44-e8c998ecd64c.jpeg</path>
	<source>
		<database>Unknown</database>
	</source>
	<size>
		<width>368</width>
		<height>490</height>
		<depth>3</depth>
	</size>
	<segmented>0</segmented>
	<object>
		<name>scooter</name>
		<pose>Unspecified</pose>
		<truncated>1</truncated>
		<difficult>0</difficult>
		<bndbox>
			<xmin>37</xmin>
			<ymin>2</ymin>
			<xmax>218</xmax>
			<ymax>490</ymax>
		</bndbox>
	</object>
</annotation>
